mwtokenizer/__init__.py
mwtokenizer/tokenizer.py
mwtokenizer/utils.py
mwtokenizer/assets/__init__.py
mwtokenizer/assets/dict_abbr_filtered.json
mwtokenizer/assets/spcmodels/__init__.py
mwtokenizer/assets/spcmodels/nws_bpe_gan.model
mwtokenizer/assets/spcmodels/nws_bpe_gan.vocab
mwtokenizer/assets/spcmodels/nws_bpe_ja.model
mwtokenizer/assets/spcmodels/nws_bpe_ja.vocab
mwtokenizer/assets/spcmodels/nws_bpe_km.model
mwtokenizer/assets/spcmodels/nws_bpe_km.vocab
mwtokenizer/assets/spcmodels/nws_bpe_lo.model
mwtokenizer/assets/spcmodels/nws_bpe_lo.vocab
mwtokenizer/assets/spcmodels/nws_bpe_my.model
mwtokenizer/assets/spcmodels/nws_bpe_my.vocab
mwtokenizer/assets/spcmodels/nws_bpe_th.model
mwtokenizer/assets/spcmodels/nws_bpe_th.vocab
mwtokenizer/assets/spcmodels/nws_bpe_wuu.model
mwtokenizer/assets/spcmodels/nws_bpe_wuu.vocab
mwtokenizer/assets/spcmodels/nws_bpe_zh.model
mwtokenizer/assets/spcmodels/nws_bpe_zh.vocab
mwtokenizer/assets/spcmodels/nws_bpe_zh_classical.model
mwtokenizer/assets/spcmodels/nws_bpe_zh_classical.vocab
mwtokenizer/assets/spcmodels/nws_bpe_zh_min_nan.model
mwtokenizer/assets/spcmodels/nws_bpe_zh_min_nan.vocab
mwtokenizer/assets/spcmodels/nws_bpe_zh_yue.model
mwtokenizer/assets/spcmodels/nws_bpe_zh_yue.vocab
mwtokenizer/assets/spcmodels/spc_bpe_tib.model
mwtokenizer/assets/spcmodels/spc_bpe_tib.vocab
mwtokenizer/config/__init__.py
mwtokenizer/config/symbols.py
mwtokenizer-0.2.0.dist-info/LICENSE
mwtokenizer-0.2.0.dist-info/METADATA
mwtokenizer-0.2.0.dist-info/WHEEL
mwtokenizer-0.2.0.dist-info/top_level.txt
mwtokenizer-0.2.0.dist-info/RECORD
