Metadata-Version: 2.1
Name: mwtokenizer
Version: 0.2.0
Summary: Wikipedia Tokenizer Utility
Home-page: https://gitlab.wikimedia.org/repos/research/wiki-nlp-tools/
Author: Aisha Khatun & Appledora & Isaac Johnson & Martin Gerlach
Author-email: <isaac@wikimedia.org>
License: MIT License
Keywords: python,wikipedia,nlp,tokenizer
Classifier: Development Status :: 4 - Beta
Classifier: License :: OSI Approved :: MIT License
Classifier: Natural Language :: English
Classifier: Programming Language :: Python :: 3
Classifier: Programming Language :: Python :: 3.7
Classifier: Programming Language :: Python :: 3.8
Classifier: Programming Language :: Python :: 3.9
Classifier: Programming Language :: Python :: 3.10
Classifier: Operating System :: Unix
Classifier: Operating System :: MacOS :: MacOS X
Classifier: Operating System :: Microsoft :: Windows
License-File: LICENSE
Requires-Dist: regex
Requires-Dist: sentencepiece
Provides-Extra: benchmarking
Requires-Dist: pandas ; extra == 'benchmarking'
Provides-Extra: dev
Requires-Dist: pytest >=6.2.5 ; extra == 'dev'
Requires-Dist: pre-commit ; extra == 'dev'
Requires-Dist: pandas ; extra == 'dev'
Provides-Extra: pre-commit
Requires-Dist: pre-commit ; extra == 'pre-commit'
Provides-Extra: tests
Requires-Dist: pytest >=6.2.5 ; extra == 'tests'
